[
  {
    "id": 0,
    "fen_string": "BBYY|BYYR|BBYY|BBYR|YRRR/-/-----|-----|-----|-----|-----/-|--|---|----|-----/-/-----|-----|-----|-----|-----/-|--|---|----|-----/-/0,0/1/0",
    "description": "Generated position 1",
    "created_at": 1754526494.340648
  },
  {
    "id": 1,
    "fen_string": "BBBY|BBYY|BBBR|BBBY|BRRK/-/-----|-----|-----|-----|-----/-|--|---|----|-----/-/-----|-----|-----|-----|-----/-|--|---|----|-----/-/0,0/1/0",
    "description": "Generated position 2",
    "created_at": 1754526494.340648
  },
  {
    "id": 2,
    "fen_string": "YRRK|BBBB|BYYY|BBBY|BBYR/-/-----|-----|-----|-----|-----/-|--|---|----|-----/-/-----|-----|-----|-----|-----/-|--|---|----|-----/-/0,0/1/0",
    "description": "Generated position 3",
    "created_at": 1754526494.340648
  },
  {
    "id": 3,
    "fen_string": "BYRR|BBYY|BBBY|BBYR|YYRR/-/-----|-----|-----|-----|-----/-|--|---|----|-----/-/-----|-----|-----|-----|-----/-|--|---|----|-----/-/0,0/1/0",
    "description": "Generated position 4",
    "created_at": 1754526494.340648
  },
  {
    "id": 4,
    "fen_string": "BBBY|BBYY|BBBY|BYYR|BBYK/-/-----|-----|-----|-----|-----/-|--|---|----|-----/-/-----|-----|-----|-----|-----/-|--|---|----|-----/-/0,0/1/0",
    "description": "Generated position 5",
    "created_at": 1754526494.340648
  },
  {
    "id": 5,
    "fen_string": "BBBY|BBBY|BBBY|BBBY|BYRK/-/-----|-----|-----|-----|-----/-|--|---|----|-----/-/-----|-----|-----|-----|-----/-|--|---|----|-----/-/0,0/1/0",
    "description": "Generated position 6",
    "created_at": 1754526494.340648
  },
  {
    "id": 6,
    "fen_string": "BBBY|BBYY|BBYY|BBBR|YYRR/-/-----|-----|-----|-----|-----/-|--|---|----|-----/-/-----|-----|-----|-----|-----/-|--|---|----|-----/-/0,0/1/0",
    "description": "Generated position 7",
    "created_at": 1754526494.341148
  },
  {
    "id": 7,
    "fen_string": "BBYR|BBYY|BBBY|BYYY|YYRR/-/-----|-----|-----|-----|-----/-|--|---|----|-----/-/-----|-----|-----|-----|-----/-|--|---|----|-----/-/0,0/1/0",
    "description": "Generated position 8",
    "created_at": 1754526494.341148
  },
  {
    "id": 8,
    "fen_string": "BBBY|BBYR|BYRR|BBYY|BRKK/-/-----|-----|-----|-----|-----/-|--|---|----|-----/-/-----|-----|-----|-----|-----/-|--|---|----|-----/-/0,0/1/0",
    "description": "Generated position 9",
    "created_at": 1754526494.341148
  },
  {
    "id": 9,
    "fen_string": "YRRR|BYYY|YYRK|BBBY|YYKK/-/-----|-----|-----|-----|-----/-|--|---|----|-----/-/-----|-----|-----|-----|-----/-|--|---|----|-----/-/0,0/1/0",
    "description": "Generated position 10",
    "created_at": 1754526494.341148
  },
  {
    "id": 10,
    "fen_string": "BBBR|BYYR|BBBY|BYRK|YYKK/-/-----|-----|-----|-----|-----/-|--|---|----|-----/-/-----|-----|-----|-----|-----/-|--|---|----|-----/-/0,0/1/0",
    "description": "Generated position 11",
    "created_at": 1754526494.341148
  },
  {
    "id": 11,
    "fen_string": "BBYY|BBYY|BBBY|BBYY|BRRR/-/-----|-----|-----|-----|-----/-|--|---|----|-----/-/-----|-----|-----|-----|-----/-|--|---|----|-----/-/0,0/1/0",
    "description": "Generated position 12",
    "created_at": 1754526494.341148
  },
  {
    "id": 12,
    "fen_string": "BBBY|BBBR|BRRR|BYYY|BYYR/-/-----|-----|-----|-----|-----/-|--|---|----|-----/-/-----|-----|-----|-----|-----/-|--|---|----|-----/-/0,0/1/0",
    "description": "Generated position 13",
    "created_at": 1754526494.341148
  },
  {
    "id": 13,
    "fen_string": "BBYY|YRRK|BYYR|BYYY|YYYR/-/-----|-----|-----|-----|-----/-|--|---|----|-----/-/-----|-----|-----|-----|-----/-|--|---|----|-----/-/0,0/1/0",
    "description": "Generated position 14",
    "created_at": 1754526494.341148
  },
  {
    "id": 14,
    "fen_string": "BBYR|BBBY|BBYY|BYYY|BBYR/-/-----|-----|-----|-----|-----/-|--|---|----|-----/-/-----|-----|-----|-----|-----/-|--|---|----|-----/-/0,0/1/0",
    "description": "Generated position 15",
    "created_at": 1754526494.341148
  },
  {
    "id": 15,
    "fen_string": "YYYR|BBYY|BBYY|BBYY|BBBB/-/-----|-----|-----|-----|-----/-|--|---|----|-----/-/-----|-----|-----|-----|-----/-|--|---|----|-----/-/0,0/1/0",
    "description": "Generated position 16",
    "created_at": 1754526494.341148
  },
  {
    "id": 16,
    "fen_string": "BBBB|BBYR|BYYY|YYRR|BYYY/-/-----|-----|-----|-----|-----/-|--|---|----|-----/-/-----|-----|-----|-----|-----/-|--|---|----|-----/-/0,0/1/0",
    "description": "Generated position 17",
    "created_at": 1754526494.341148
  },
  {
    "id": 17,
    "fen_string": "BBBB|BBRR|BBBB|BBYY|YYRR/-/-----|-----|-----|-----|-----/-|--|---|----|-----/-/-----|-----|-----|-----|-----/-|--|---|----|-----/-/0,0/1/0",
    "description": "Generated position 18",
    "created_at": 1754526494.341148
  },
  {
    "id": 18,
    "fen_string": "BYYR|BBYY|BBBY|BBYY|BYYY/-/-----|-----|-----|-----|-----/-|--|---|----|-----/-/-----|-----|-----|-----|-----/-|--|---|----|-----/-/0,0/1/0",
    "description": "Generated position 19",
    "created_at": 1754526494.341148
  },
  {
    "id": 19,
    "fen_string": "BBYY|BBBR|BBBB|BYRR|BYRR/-/-----|-----|-----|-----|-----/-|--|---|----|-----/-/-----|-----|-----|-----|-----/-|--|---|----|-----/-/0,0/1/0",
    "description": "Generated position 20",
    "created_at": 1754526494.341148
  },
  {
    "id": 20,
    "fen_string": "BBYY|RKKK|BBBY|BYYR|YYRR/-/-----|-----|-----|-----|-----/-|--|---|----|-----/-/-----|-----|-----|-----|-----/-|--|---|----|-----/-/0,0/1/0",
    "description": "Generated position 21",
    "created_at": 1754526494.341148
  },
  {
    "id": 21,
    "fen_string": "BBBB|BBBY|BBBR|BBBY|BBYR/-/-----|-----|-----|-----|-----/-|--|---|----|-----/-/-----|-----|-----|-----|-----/-|--|---|----|-----/-/0,0/1/0",
    "description": "Generated position 22",
    "created_at": 1754526494.341148
  },
  {
    "id": 22,
    "fen_string": "BYYY|BBBB|BYYR|YRRK|YRKK/-/-----|-----|-----|-----|-----/-|--|---|----|-----/-/-----|-----|-----|-----|-----/-|--|---|----|-----/-/0,0/1/0",
    "description": "Generated position 23",
    "created_at": 1754526494.341148
  },
  {
    "id": 23,
    "fen_string": "BYYR|YYYR|BBYY|BBYY|BBBR/-/-----|-----|-----|-----|-----/-|--|---|----|-----/-/-----|-----|-----|-----|-----/-|--|---|----|-----/-/0,0/1/0",
    "description": "Generated position 24",
    "created_at": 1754526494.341148
  },
  {
    "id": 24,
    "fen_string": "BBRR|BBYR|BBBY|BYRR|BBYY/-/-----|-----|-----|-----|-----/-|--|---|----|-----/-/-----|-----|-----|-----|-----/-|--|---|----|-----/-/0,0/1/0",
    "description": "Generated position 25",
    "created_at": 1754526494.3418055
  },
  {
    "id": 25,
    "fen_string": "BYYY|BYYY|YRKK|BBYY|BYRR/-/-----|-----|-----|-----|-----/-|--|---|----|-----/-/-----|-----|-----|-----|-----/-|--|---|----|-----/-/0,0/1/0",
    "description": "Generated position 26",
    "created_at": 1754526494.3418055
  },
  {
    "id": 26,
    "fen_string": "BYYR|BBYW|BYYR|BYYY|BYRR/-/-----|-----|-----|-----|-----/-|--|---|----|-----/-/-----|-----|-----|-----|-----/-|--|---|----|-----/-/0,0/1/0",
    "description": "Generated position 27",
    "created_at": 1754526494.3418055
  },
  {
    "id": 27,
    "fen_string": "BBBR|BBYK|BYYY|BYYY|YYYK/-/-----|-----|-----|-----|-----/-|--|---|----|-----/-/-----|-----|-----|-----|-----/-|--|---|----|-----/-/0,0/1/0",
    "description": "Generated position 28",
    "created_at": 1754526494.3418055
  },
  {
    "id": 28,
    "fen_string": "BBBB|BBYY|BBBK|RKKW|YKWW/-/BYRK-|-BY-K|K--Y-|--WBY|YR-W-/-|Y-|KK-|----|-----/KR/-Y-KW|W--R-|-WBYR|-K---|--KWB/B|Y-|RRR|----|-----/RB/0,0/1/0",
    "description": "Generated position 29",
    "created_at": 1754526494.3418055
  },
  {
    "id": 29,
    "fen_string": "BBYY|BBYY|BRRK|RRRW|YYKW/-/-Y-KW|--Y-K|K-BY-|--W-Y|Y-KW-/B|W-|KKK|----|-----/RY/B-RKW|W--RK|-W--R|-KW--|-RK-B/-|BB|---|----|-----/WY/0,0/1/0",
    "description": "Generated position 30",
    "created_at": 1754526494.3418055
  },
  {
    "id": 30,
    "fen_string": "BYKW|BYYY|BBRR|YYRR|YYRK/-/BY-KW|-BYR-|KW-Y-|-K---|YRK--/-|K-|RRR|----|-----/KR/--RK-|-B---|KWBY-|RKW-Y|-R-W-/W|--|---|----|-----/BY/0,0/1/0",
    "description": "Generated position 31",
    "created_at": 1754526494.3418055
  },
  {
    "id": 31,
    "fen_string": "BYYK|RRRR|BBBY|YYYK|BWWW/-/B-R--|WBY--|-WB--|R----|YRKWB/W|--|RR-|----|-----/RW/--R-W|WBY-K|K----|R-W-Y|YRKW-/-|YY|RRR|----|-----/BB/0,0/1/0",
    "description": "Generated position 32",
    "created_at": 1754526494.3418055
  },
  {
    "id": 32,
    "fen_string": "BBYY|YRRR|BBYR|BBYY|YRKW/-/-YR-W|-BY-K|--B-R|R--BY|--KW-/K|R-|RRR|----|-----/WB/B-RKW|--Y-K|KWBY-|--WB-|-R---/R|Y-|---|----|-----/RR/0,0/1/0",
    "description": "Generated position 33",
    "created_at": 1754526494.3418055
  },
  {
    "id": 33,
    "fen_string": "BYYW|BBBB|BBYR|BBYY|KKKK/-/B---W|W-YRK|K--Y-|--WB-|Y--W-/Y|--|WWW|----|-----/KY/-YR-W|-B---|K--YR|---B-|YRKWB/-|--|---|----|-----/YY/0,0/1/0",
    "description": "Generated position 34",
    "created_at": 1754526494.3418055
  },
  {
    "id": 34,
    "fen_string": "BBRR|BBBK|BBYY|YKWW|RRKW/-/-Y-K-|W----|KWBYR|-----|-RK-B/B|W-|KKK|----|-----/RB/----W|W-YRK|K---R|-KW--|Y-KWB/Y|--|YY-|----|-----/RB/0,0/1/0",
    "description": "Generated position 35",
    "created_at": 1754526494.342311
  },
  {
    "id": 35,
    "fen_string": "BBRR|YRKK|YYRR|BYRW|YYKW/-/-Y-KW|WBY--|---Y-|----Y|--K-B/B|WW|BBB|----|-----/KB/BYRK-|W--R-|K-BY-|--WB-|--K-B/R|--|YYY|----|-----/KB/0,0/1/0",
    "description": "Generated position 36",
    "created_at": 1754526494.342311
  },
  {
    "id": 36,
    "fen_string": "BBRK|BRRR|BBRK|BYYY|RRKW/-/BYR--|WBY--|-W-Y-|R---Y|Y--W-/W|--|---|----|-----/RW/-YRK-|WB--K|K--YR|R-WB-|-R--B/Y|--|WW-|----|-----/YR/0,0/1/0",
    "description": "Generated position 37",
    "created_at": 1754526494.342311
  },
  {
    "id": 37,
    "fen_string": "YYRR|BYRW|BYYY|BBYK|YYYR/-/B--K-|W--R-|KWB--|R-W-Y|-RK--/K|--|---|----|-----/YK/BYRK-|--YR-|-W-Y-|RKWBY|---WB/-|--|WW-|----|-----/YW/0,0/1/0",
    "description": "Generated position 38",
    "created_at": 1754526494.342311
  },
  {
    "id": 38,
    "fen_string": "YYRR|BYKW|BYYY|BRRK|RKKK/-/-YR-W|-BY--|K-B-R|R--B-|-R-WB/K|RR|YY-|----|-----/YR/---K-|W----|KWB--|-KWB-|Y-KWB/R|K-|WW-|----|-----/RK/0,0/1/0",
    "description": "Generated position 39",
    "created_at": 1754526494.342311
  },
  {
    "id": 39,
    "fen_string": "BRRK|BYRK|BBYK|BBYR|BYYK/-/---KW|--YRK|--B--|R--BY|-RKWB/Y|YY|---|----|-----/BR/BYRK-|---RK|KW-Y-|-K-B-|Y--W-/-|KK|---|----|-----/BR/0,0/1/0",
    "description": "Generated position 40",
    "created_at": 1754526494.342311
  },
  {
    "id": 40,
    "fen_string": "BYYY|BBYR|BYYK|YRRR|BBRK/-/-YR-W|W-Y--|KW---|R--BY|Y---B/K|RR|RR-|----|-----/YY/B-RK-|-BY--|K---R|-KWB-|-R---/B|YY|RR-|----|-----/KY/0,0/1/0",
    "description": "Generated position 41",
    "created_at": 1754526494.342311
  },
  {
    "id": 41,
    "fen_string": "BYYY|BRRR|BYYR|BYYY|WWWW/-/B-RK-|--YRK|-W-YR|R-W--|-R---/B|R-|BBB|----|-----/WK/B-R-W|W-YRK|-----|R-W-Y|YR--B/R|R-|YY-|----|-----/WY/0,0/1/0",
    "description": "Generated position 42",
    "created_at": 1754526494.342311
  }
]